llm_bhasa/__init__.py
llm_bhasa/harmony/__init__.py
llm_bhasa/harmony/attention.py
llm_bhasa/harmony/config.py
llm_bhasa/harmony/data.py
llm_bhasa/harmony/dataset.py
llm_bhasa/harmony/generator.py
llm_bhasa/harmony/model.py
llm_bhasa/harmony/tokenizer.py
llm_bhasa/harmony/training.py
llm_bhasa/harmony/tasks/__init__.py
llm_bhasa/harmony/tasks/classify.py
llm_bhasa/harmony/tasks/instruction_finetune.py
llm_bhasa-0.5.dist-info/METADATA
llm_bhasa-0.5.dist-info/WHEEL
llm_bhasa-0.5.dist-info/top_level.txt
llm_bhasa-0.5.dist-info/RECORD
